mlflow2sql/__init__.py
mlflow2sql/export.py
mlflow2sql/generate.py
mlflow2sql/ml.py
mlflow2sql-0.1.dist-info/LICENSE
mlflow2sql-0.1.dist-info/METADATA
mlflow2sql-0.1.dist-info/WHEEL
mlflow2sql-0.1.dist-info/top_level.txt
mlflow2sql-0.1.dist-info/RECORD
