Metadata-Version: 2.1
Name: mlflow2sql
Version: 0.1
License-File: LICENSE
Requires-Dist: pyyaml
Provides-Extra: demo
Requires-Dist: scikit-learn ; extra == 'demo'
Requires-Dist: matplotlib ; extra == 'demo'
Requires-Dist: sklearn-evaluation ; extra == 'demo'
Requires-Dist: mlflow ; extra == 'demo'
Provides-Extra: dev
Requires-Dist: pkgmt ; extra == 'dev'
Requires-Dist: pytest ; extra == 'dev'
Requires-Dist: flake8 ; extra == 'dev'
Requires-Dist: invoke ; extra == 'dev'
Requires-Dist: twine ; extra == 'dev'
Requires-Dist: mlflow ; extra == 'dev'
Requires-Dist: numpy ; extra == 'dev'
Requires-Dist: psutil ; extra == 'dev'
Requires-Dist: matplotlib ; extra == 'dev'
